texgit/__init__.py
texgit/py.typed
texgit/run.py
texgit/version.py
texgit/formatters/__init__.py
texgit/formatters/python.py
texgit/formatters/source_tools.py
texgit/repository/__init__.py
texgit/repository/file_manager.py
texgit/repository/fix_path.py
texgit/repository/git.py
texgit/repository/git_manager.py
texgit/repository/process_manager.py
texgit-0.9.10.dist-info/METADATA
texgit-0.9.10.dist-info/WHEEL
texgit-0.9.10.dist-info/top_level.txt
texgit-0.9.10.dist-info/RECORD
