Metadata-Version: 2.4
Name: texgit
Version: 0.9.10
Summary: A package for metaheuristic optimization in Python.
Home-page: https://thomasweise.github.io/texgit_py
Author: Thomas Weise
Author-email: tweise@ustc.edu.cn
Maintainer: Thomas Weise
Maintainer-email: tweise@ustc.edu.cn
License: GPL 3.0
Project-URL: Documentation, https://thomasweise.github.io/texgit_py
Project-URL: Source, https://github.com/thomasWeise/texgit_py/
Project-URL: Tracker, https://github.com/thomasWeise/texgit_py/issues
Keywords: LaTeX,git
Classifier: Development Status :: 4 - Beta
Classifier: Intended Audience :: Developers
Classifier: Intended Audience :: Education
Classifier: License :: OSI Approved :: GNU General Public License v3 (GPLv3)
Classifier: Natural Language :: English
Classifier: Operating System :: POSIX :: Linux
Classifier: Programming Language :: Python :: 3 :: Only
Classifier: Programming Language :: Python :: 3.12
Requires-Python: >=3.12
Requires-Dist: pycommons>=0.8.69
Requires-Dist: strip-hints>=0.1.13
Requires-Dist: yapf>=0.43.0
Dynamic: description
Dynamic: description-content-type
